{
    "954183": {
        "startTime": "Thu Oct 10 07:36:51 CDT 2019",
        "user": "rafiisla"
    },
    "954188": {
        "startTime": "Thu Oct 10 09:59:56 CDT 2019",
        "user": "rafiisla"
    },
    "954192": {
        "startTime": "Wed Oct 09 08:13:47 CDT 2019",
        "user": "rafiisla"
    },
    "954197": {
        "startTime": "Thu Oct 10 10:36:42 CDT 2019",
        "user": "rafiisla"
    },
    "954202": {
        "startTime": "Thu Oct 10 11:24:23 CDT 2019",
        "user": "rafiisla"
    },
    "958807": {
        "startTime": "Mon Oct 07 15:24:40 CDT 2019",
        "user": "ssukumar"
    },
    "960443": {
        "startTime": "Tue Oct 08 15:28:26 CDT 2019",
        "user": "andhingr"
    },
    "960445": {
        "startTime": "Tue Oct 08 15:29:11 CDT 2019",
        "user": "andhingr"
    },
    "960494": {
        "startTime": "Tue Oct 08 15:34:30 CDT 2019",
        "user": "andhingr"
    },
    "960495": {
        "startTime": "Tue Oct 08 15:35:16 CDT 2019",
        "user": "andhingr"
    },
    "960498": {
        "startTime": "Tue Oct 08 15:38:22 CDT 2019",
        "user": "andhingr"
    },
    "960501": {
        "startTime": "Tue Oct 08 15:42:43 CDT 2019",
        "user": "andhingr"
    },
    "960638": {
        "startTime": "Tue Oct 08 17:28:51 CDT 2019",
        "user": "abdumali"
    },
    "960660": {
        "startTime": "Tue Oct 08 17:28:51 CDT 2019",
        "user": "abdumali"
    },
    "960664": {
        "startTime": "Tue Oct 08 17:28:51 CDT 2019",
        "user": "abdumali"
    },
    "960783": {
        "startTime": "Tue Oct 08 17:28:51 CDT 2019",
        "user": "abdumali"
    },
    "960812": {
        "startTime": "Tue Oct 08 17:29:10 CDT 2019",
        "user": "abdumali"
    },
    "960818": {
        "startTime": "Tue Oct 08 17:29:10 CDT 2019",
        "user": "abdumali"
    },
    "960850": {
        "startTime": "Tue Oct 08 17:29:10 CDT 2019",
        "user": "abdumali"
    },
    "960900": {
        "startTime": "Tue Oct 08 17:29:10 CDT 2019",
        "user": "abdumali"
    },
    "960901": {
        "startTime": "Tue Oct 08 17:29:10 CDT 2019",
        "user": "abdumali"
    },
    "960936": {
        "startTime": "Tue Oct 08 17:29:10 CDT 2019",
        "user": "abdumali"
    },
    "961001": {
        "startTime": "Tue Oct 08 17:29:29 CDT 2019",
        "user": "abdumali"
    },
    "961029": {
        "startTime": "Tue Oct 08 17:29:29 CDT 2019",
        "user": "abdumali"
    },
    "961045": {
        "startTime": "Tue Oct 08 17:29:29 CDT 2019",
        "user": "abdumali"
    },
    "961051": {
        "startTime": "Tue Oct 08 17:29:29 CDT 2019",
        "user": "abdumali"
    },
    "961059": {
        "startTime": "Tue Oct 08 17:29:29 CDT 2019",
        "user": "abdumali"
    },
    "961086": {
        "startTime": "Tue Oct 08 17:29:29 CDT 2019",
        "user": "abdumali"
    },
    "961088": {
        "startTime": "Tue Oct 08 17:29:29 CDT 2019",
        "user": "abdumali"
    },
    "961152": {
        "startTime": "Tue Oct 08 17:29:29 CDT 2019",
        "user": "abdumali"
    },
    "961168": {
        "startTime": "Tue Oct 08 17:29:29 CDT 2019",
        "user": "abdumali"
    },
    "961190": {
        "startTime": "Tue Oct 08 17:29:46 CDT 2019",
        "user": "abdumali"
    },
    "961202": {
        "startTime": "Tue Oct 08 17:29:46 CDT 2019",
        "user": "abdumali"
    },
    "961206": {
        "startTime": "Tue Oct 08 17:29:46 CDT 2019",
        "user": "abdumali"
    },
    "961220": {
        "startTime": "Tue Oct 08 17:29:46 CDT 2019",
        "user": "abdumali"
    },
    "961239": {
        "startTime": "Tue Oct 08 17:29:46 CDT 2019",
        "user": "abdumali"
    },
    "961258": {
        "startTime": "Tue Oct 08 17:29:46 CDT 2019",
        "user": "abdumali"
    },
    "961264": {
        "startTime": "Tue Oct 08 17:29:46 CDT 2019",
        "user": "abdumali"
    },
    "961265": {
        "startTime": "Tue Oct 08 17:29:46 CDT 2019",
        "user": "abdumali"
    },
    "961269": {
        "startTime": "Tue Oct 08 17:29:46 CDT 2019",
        "user": "abdumali"
    },
    "961286": {
        "startTime": "Tue Oct 08 17:29:46 CDT 2019",
        "user": "abdumali"
    },
    "961316": {
        "startTime": "Tue Oct 08 17:29:46 CDT 2019",
        "user": "abdumali"
    },
    "961424": {
        "startTime": "Tue Oct 08 17:30:03 CDT 2019",
        "user": "abdumali"
    },
    "961431": {
        "startTime": "Tue Oct 08 17:30:03 CDT 2019",
        "user": "abdumali"
    },
    "961470": {
        "startTime": "Tue Oct 08 17:30:03 CDT 2019",
        "user": "abdumali"
    },
    "961793": {
        "startTime": "Tue Oct 08 22:14:56 CDT 2019",
        "user": "hge"
    },
    "961891": {
        "startTime": "Tue Oct 08 22:19:08 CDT 2019",
        "user": "nayshah"
    },
    "961892": {
        "startTime": "Tue Oct 08 22:19:22 CDT 2019",
        "user": "nayshah"
    },
    "961893": {
        "startTime": "Tue Oct 08 22:19:34 CDT 2019",
        "user": "nayshah"
    },
    "961894": {
        "startTime": "Tue Oct 08 22:19:34 CDT 2019",
        "user": "nayshah"
    },
    "961895": {
        "startTime": "Tue Oct 08 22:19:34 CDT 2019",
        "user": "nayshah"
    },
    "961896": {
        "startTime": "Tue Oct 08 22:19:35 CDT 2019",
        "user": "nayshah"
    },
    "961897": {
        "startTime": "Tue Oct 08 22:19:47 CDT 2019",
        "user": "nayshah"
    },
    "961898": {
        "startTime": "Tue Oct 08 22:19:47 CDT 2019",
        "user": "nayshah"
    },
    "961899": {
        "startTime": "Tue Oct 08 22:19:48 CDT 2019",
        "user": "nayshah"
    },
    "961900": {
        "startTime": "Tue Oct 08 22:20:00 CDT 2019",
        "user": "nayshah"
    },
    "961901": {
        "startTime": "Tue Oct 08 22:20:00 CDT 2019",
        "user": "nayshah"
    },
    "961903": {
        "startTime": "Wed Oct 09 03:17:24 CDT 2019",
        "user": "jieyao"
    },
    "961906": {
        "startTime": "Wed Oct 09 02:57:57 CDT 2019",
        "user": "fazhussa"
    },
    "961907": {
        "startTime": "Thu Oct 10 09:26:17 CDT 2019",
        "user": "fazhussa"
    },
    "961999": {
        "startTime": "Thu Oct 10 14:48:09 CDT 2019",
        "user": "llindblo"
    },
    "962007": {
        "startTime": "Wed Oct 09 05:23:20 CDT 2019",
        "user": "lediaz"
    },
    "962065": {
        "startTime": "Wed Oct 09 09:42:28 CDT 2019",
        "user": "malooney"
    },
    "962168": {
        "startTime": "Wed Oct 09 10:22:27 CDT 2019",
        "user": "aaljadda"
    },
    "962298": {
        "startTime": "Wed Oct 09 11:16:11 CDT 2019",
        "user": "bjayee"
    },
    "962299": {
        "startTime": "Wed Oct 09 20:40:49 CDT 2019",
        "user": "thongle"
    },
    "962300": {
        "startTime": "Wed Oct 09 11:16:14 CDT 2019",
        "user": "bjayee"
    },
    "962301": {
        "startTime": "Wed Oct 09 11:16:14 CDT 2019",
        "user": "bjayee"
    },
    "962303": {
        "startTime": "Wed Oct 09 12:03:24 CDT 2019",
        "user": "bjayee"
    },
    "962304": {
        "startTime": "Wed Oct 09 12:04:33 CDT 2019",
        "user": "bjayee"
    },
    "962316": {
        "startTime": "Wed Oct 09 12:05:52 CDT 2019",
        "user": "bjayee"
    },
    "962361": {
        "startTime": "Thu Oct 10 02:25:14 CDT 2019",
        "user": "thongle"
    },
    "962364": {
        "startTime": "Thu Oct 10 04:11:33 CDT 2019",
        "user": "thongle"
    },
    "962369": {
        "startTime": "Thu Oct 10 04:28:19 CDT 2019",
        "user": "thongle"
    },
    "962396": {
        "startTime": "Wed Oct 09 23:00:08 CDT 2019",
        "user": "rmuthuku"
    },
    "962495": {
        "startTime": "Wed Oct 09 14:36:50 CDT 2019",
        "user": "bjayee"
    },
    "962496": {
        "startTime": "Wed Oct 09 16:50:06 CDT 2019",
        "user": "bjayee"
    },
    "962497": {
        "startTime": "Wed Oct 09 20:40:46 CDT 2019",
        "user": "bjayee"
    },
    "962498": {
        "startTime": "Wed Oct 09 20:40:48 CDT 2019",
        "user": "bjayee"
    },
    "962525": {
        "startTime": "Thu Oct 10 00:26:18 CDT 2019",
        "user": "nayshah"
    },
    "962535": {
        "startTime": "Thu Oct 10 00:48:24 CDT 2019",
        "user": "nayshah"
    },
    "962541": {
        "startTime": "Thu Oct 10 02:26:52 CDT 2019",
        "user": "nayshah"
    },
    "962547": {
        "startTime": "Thu Oct 10 04:28:29 CDT 2019",
        "user": "nayshah"
    },
    "962552": {
        "startTime": "Thu Oct 10 04:28:53 CDT 2019",
        "user": "nayshah"
    },
    "962557": {
        "startTime": "Thu Oct 10 05:51:44 CDT 2019",
        "user": "nayshah"
    },
    "962558": {
        "startTime": "Thu Oct 10 05:51:44 CDT 2019",
        "user": "nayshah"
    },
    "962559": {
        "startTime": "Thu Oct 10 05:51:44 CDT 2019",
        "user": "nayshah"
    },
    "962560": {
        "startTime": "Thu Oct 10 06:41:18 CDT 2019",
        "user": "nayshah"
    },
    "962561": {
        "startTime": "Thu Oct 10 06:41:28 CDT 2019",
        "user": "nayshah"
    },
    "962562": {
        "startTime": "Thu Oct 10 06:41:28 CDT 2019",
        "user": "nayshah"
    },
    "962637": {
        "startTime": "Wed Oct 09 14:44:16 CDT 2019",
        "user": "yuxyao"
    },
    "962738": {
        "startTime": "Wed Oct 09 15:50:51 CDT 2019",
        "user": "snafees"
    },
    "962945": {
        "startTime": "Thu Oct 10 04:28:29 CDT 2019",
        "user": "tivincen"
    },
    "962946": {
        "startTime": "Thu Oct 10 04:28:30 CDT 2019",
        "user": "tivincen"
    },
    "962947": {
        "startTime": "Thu Oct 10 04:28:42 CDT 2019",
        "user": "tivincen"
    },
    "962948": {
        "startTime": "Thu Oct 10 05:51:29 CDT 2019",
        "user": "tivincen"
    },
    "962950": {
        "startTime": "Wed Oct 09 17:47:06 CDT 2019",
        "user": "roshang"
    },
    "962954": {
        "startTime": "Wed Oct 09 23:34:04 CDT 2019",
        "user": "lediaz"
    },
    "962955": {
        "startTime": "Wed Oct 09 23:35:09 CDT 2019",
        "user": "lediaz"
    },
    "962956": {
        "startTime": "Wed Oct 09 23:42:25 CDT 2019",
        "user": "lediaz"
    },
    "962957": {
        "startTime": "Wed Oct 09 23:47:29 CDT 2019",
        "user": "lediaz"
    },
    "962960": {
        "startTime": "Wed Oct 09 19:15:15 CDT 2019",
        "user": "zha98475"
    },
    "962975": {
        "startTime": "Wed Oct 09 19:39:34 CDT 2019",
        "user": "abdumali"
    },
    "962977": {
        "startTime": "Wed Oct 09 19:39:34 CDT 2019",
        "user": "abdumali"
    },
    "962981": {
        "startTime": "Wed Oct 09 19:39:34 CDT 2019",
        "user": "abdumali"
    },
    "962993": {
        "startTime": "Wed Oct 09 19:39:34 CDT 2019",
        "user": "abdumali"
    },
    "962995": {
        "startTime": "Wed Oct 09 19:39:34 CDT 2019",
        "user": "abdumali"
    },
    "963000": {
        "startTime": "Wed Oct 09 19:39:34 CDT 2019",
        "user": "abdumali"
    },
    "963009": {
        "startTime": "Wed Oct 09 19:39:34 CDT 2019",
        "user": "abdumali"
    },
    "963012": {
        "startTime": "Wed Oct 09 19:39:34 CDT 2019",
        "user": "abdumali"
    },
    "963018": {
        "startTime": "Wed Oct 09 19:39:34 CDT 2019",
        "user": "abdumali"
    },
    "963020": {
        "startTime": "Wed Oct 09 19:39:34 CDT 2019",
        "user": "abdumali"
    },
    "963021": {
        "startTime": "Wed Oct 09 19:39:34 CDT 2019",
        "user": "abdumali"
    },
    "963024": {
        "startTime": "Wed Oct 09 19:39:34 CDT 2019",
        "user": "abdumali"
    },
    "963041": {
        "startTime": "Wed Oct 09 19:39:34 CDT 2019",
        "user": "abdumali"
    },
    "963042": {
        "startTime": "Wed Oct 09 19:39:34 CDT 2019",
        "user": "abdumali"
    },
    "963043": {
        "startTime": "Wed Oct 09 19:39:34 CDT 2019",
        "user": "abdumali"
    },
    "963054": {
        "startTime": "Wed Oct 09 19:39:34 CDT 2019",
        "user": "abdumali"
    },
    "963059": {
        "startTime": "Wed Oct 09 19:39:34 CDT 2019",
        "user": "abdumali"
    },
    "963066": {
        "startTime": "Wed Oct 09 19:39:48 CDT 2019",
        "user": "abdumali"
    },
    "963068": {
        "startTime": "Wed Oct 09 19:39:48 CDT 2019",
        "user": "abdumali"
    },
    "963069": {
        "startTime": "Wed Oct 09 19:39:48 CDT 2019",
        "user": "abdumali"
    },
    "963083": {
        "startTime": "Wed Oct 09 19:39:48 CDT 2019",
        "user": "abdumali"
    },
    "963085": {
        "startTime": "Wed Oct 09 19:39:48 CDT 2019",
        "user": "abdumali"
    },
    "963099": {
        "startTime": "Wed Oct 09 19:39:48 CDT 2019",
        "user": "abdumali"
    },
    "963158": {
        "startTime": "Wed Oct 09 19:40:09 CDT 2019",
        "user": "abdumali"
    },
    "963171": {
        "startTime": "Wed Oct 09 19:40:24 CDT 2019",
        "user": "abdumali"
    },
    "963178": {
        "startTime": "Wed Oct 09 19:42:38 CDT 2019",
        "user": "abdumali"
    },
    "963179": {
        "startTime": "Wed Oct 09 19:42:40 CDT 2019",
        "user": "abdumali"
    },
    "963188": {
        "startTime": "Wed Oct 09 19:49:29 CDT 2019",
        "user": "abdumali"
    },
    "963191": {
        "startTime": "Wed Oct 09 19:51:03 CDT 2019",
        "user": "abdumali"
    },
    "963201": {
        "startTime": "Wed Oct 09 19:54:52 CDT 2019",
        "user": "abdumali"
    },
    "963205": {
        "startTime": "Wed Oct 09 19:55:25 CDT 2019",
        "user": "abdumali"
    },
    "963210": {
        "startTime": "Wed Oct 09 19:56:09 CDT 2019",
        "user": "abdumali"
    },
    "963215": {
        "startTime": "Wed Oct 09 19:58:32 CDT 2019",
        "user": "abdumali"
    },
    "963225": {
        "startTime": "Wed Oct 09 20:02:02 CDT 2019",
        "user": "abdumali"
    },
    "963227": {
        "startTime": "Wed Oct 09 20:02:30 CDT 2019",
        "user": "abdumali"
    },
    "963233": {
        "startTime": "Wed Oct 09 20:03:47 CDT 2019",
        "user": "abdumali"
    },
    "963234": {
        "startTime": "Wed Oct 09 20:03:47 CDT 2019",
        "user": "abdumali"
    },
    "963252": {
        "startTime": "Wed Oct 09 20:07:29 CDT 2019",
        "user": "abdumali"
    },
    "963253": {
        "startTime": "Wed Oct 09 20:07:29 CDT 2019",
        "user": "abdumali"
    },
    "963257": {
        "startTime": "Wed Oct 09 20:07:29 CDT 2019",
        "user": "abdumali"
    },
    "963262": {
        "startTime": "Wed Oct 09 20:07:41 CDT 2019",
        "user": "abdumali"
    },
    "963265": {
        "startTime": "Wed Oct 09 20:08:06 CDT 2019",
        "user": "abdumali"
    },
    "963273": {
        "startTime": "Wed Oct 09 20:08:06 CDT 2019",
        "user": "abdumali"
    },
    "963278": {
        "startTime": "Wed Oct 09 20:08:06 CDT 2019",
        "user": "abdumali"
    },
    "963291": {
        "startTime": "Wed Oct 09 20:08:06 CDT 2019",
        "user": "abdumali"
    },
    "963294": {
        "startTime": "Wed Oct 09 20:08:06 CDT 2019",
        "user": "abdumali"
    },
    "963295": {
        "startTime": "Wed Oct 09 20:08:06 CDT 2019",
        "user": "abdumali"
    },
    "963314": {
        "startTime": "Wed Oct 09 20:08:18 CDT 2019",
        "user": "abdumali"
    },
    "963319": {
        "startTime": "Wed Oct 09 20:08:18 CDT 2019",
        "user": "abdumali"
    },
    "963324": {
        "startTime": "Wed Oct 09 20:08:18 CDT 2019",
        "user": "abdumali"
    },
    "963325": {
        "startTime": "Wed Oct 09 20:08:18 CDT 2019",
        "user": "abdumali"
    },
    "963326": {
        "startTime": "Wed Oct 09 20:08:18 CDT 2019",
        "user": "abdumali"
    },
    "963328": {
        "startTime": "Wed Oct 09 20:09:52 CDT 2019",
        "user": "abdumali"
    },
    "963334": {
        "startTime": "Wed Oct 09 20:10:05 CDT 2019",
        "user": "abdumali"
    },
    "963335": {
        "startTime": "Wed Oct 09 20:10:05 CDT 2019",
        "user": "abdumali"
    },
    "963338": {
        "startTime": "Wed Oct 09 20:10:06 CDT 2019",
        "user": "abdumali"
    },
    "963342": {
        "startTime": "Wed Oct 09 20:10:18 CDT 2019",
        "user": "abdumali"
    },
    "963343": {
        "startTime": "Wed Oct 09 20:10:31 CDT 2019",
        "user": "abdumali"
    },
    "963345": {
        "startTime": "Wed Oct 09 20:11:02 CDT 2019",
        "user": "abdumali"
    },
    "963354": {
        "startTime": "Wed Oct 09 20:12:27 CDT 2019",
        "user": "abdumali"
    },
    "963358": {
        "startTime": "Wed Oct 09 20:13:30 CDT 2019",
        "user": "abdumali"
    },
    "963381": {
        "startTime": "Wed Oct 09 20:16:53 CDT 2019",
        "user": "abdumali"
    },
    "963382": {
        "startTime": "Wed Oct 09 20:17:04 CDT 2019",
        "user": "abdumali"
    },
    "963383": {
        "startTime": "Wed Oct 09 20:17:04 CDT 2019",
        "user": "abdumali"
    },
    "963387": {
        "startTime": "Wed Oct 09 20:18:03 CDT 2019",
        "user": "abdumali"
    },
    "963396": {
        "startTime": "Wed Oct 09 20:19:16 CDT 2019",
        "user": "abdumali"
    },
    "963400": {
        "startTime": "Wed Oct 09 20:19:50 CDT 2019",
        "user": "abdumali"
    },
    "963405": {
        "startTime": "Wed Oct 09 20:20:19 CDT 2019",
        "user": "abdumali"
    },
    "963407": {
        "startTime": "Wed Oct 09 20:20:19 CDT 2019",
        "user": "abdumali"
    },
    "963421": {
        "startTime": "Wed Oct 09 20:23:06 CDT 2019",
        "user": "abdumali"
    },
    "963429": {
        "startTime": "Wed Oct 09 20:24:37 CDT 2019",
        "user": "abdumali"
    },
    "963447": {
        "startTime": "Wed Oct 09 20:28:21 CDT 2019",
        "user": "abdumali"
    },
    "963449": {
        "startTime": "Wed Oct 09 20:28:31 CDT 2019",
        "user": "abdumali"
    },
    "963453": {
        "startTime": "Wed Oct 09 20:30:29 CDT 2019",
        "user": "abdumali"
    },
    "963459": {
        "startTime": "Wed Oct 09 20:31:39 CDT 2019",
        "user": "abdumali"
    },
    "963476": {
        "startTime": "Wed Oct 09 20:34:09 CDT 2019",
        "user": "abdumali"
    },
    "963477": {
        "startTime": "Wed Oct 09 20:34:17 CDT 2019",
        "user": "abdumali"
    },
    "963484": {
        "startTime": "Wed Oct 09 20:34:54 CDT 2019",
        "user": "abdumali"
    },
    "963490": {
        "startTime": "Wed Oct 09 20:35:24 CDT 2019",
        "user": "abdumali"
    },
    "963504": {
        "startTime": "Wed Oct 09 20:37:47 CDT 2019",
        "user": "abdumali"
    },
    "963512": {
        "startTime": "Wed Oct 09 20:38:54 CDT 2019",
        "user": "abdumali"
    },
    "963554": {
        "startTime": "Wed Oct 09 20:46:49 CDT 2019",
        "user": "abdumali"
    },
    "963558": {
        "startTime": "Wed Oct 09 20:47:16 CDT 2019",
        "user": "abdumali"
    },
    "963561": {
        "startTime": "Wed Oct 09 20:47:39 CDT 2019",
        "user": "abdumali"
    },
    "963564": {
        "startTime": "Wed Oct 09 20:48:19 CDT 2019",
        "user": "abdumali"
    },
    "963568": {
        "startTime": "Wed Oct 09 20:49:36 CDT 2019",
        "user": "abdumali"
    },
    "963578": {
        "startTime": "Wed Oct 09 20:51:24 CDT 2019",
        "user": "abdumali"
    },
    "963608": {
        "startTime": "Wed Oct 09 20:56:55 CDT 2019",
        "user": "abdumali"
    },
    "963622": {
        "startTime": "Wed Oct 09 20:59:13 CDT 2019",
        "user": "abdumali"
    },
    "963624": {
        "startTime": "Wed Oct 09 20:59:16 CDT 2019",
        "user": "abdumali"
    },
    "963635": {
        "startTime": "Wed Oct 09 21:02:32 CDT 2019",
        "user": "abdumali"
    },
    "963641": {
        "startTime": "Wed Oct 09 21:04:15 CDT 2019",
        "user": "abdumali"
    },
    "963642": {
        "startTime": "Wed Oct 09 21:04:18 CDT 2019",
        "user": "abdumali"
    },
    "963649": {
        "startTime": "Wed Oct 09 21:08:45 CDT 2019",
        "user": "abdumali"
    },
    "963651": {
        "startTime": "Wed Oct 09 21:09:18 CDT 2019",
        "user": "abdumali"
    },
    "963652": {
        "startTime": "Wed Oct 09 21:09:30 CDT 2019",
        "user": "abdumali"
    },
    "963658": {
        "startTime": "Wed Oct 09 21:12:26 CDT 2019",
        "user": "abdumali"
    },
    "963667": {
        "startTime": "Wed Oct 09 21:21:19 CDT 2019",
        "user": "abdumali"
    },
    "963676": {
        "startTime": "Wed Oct 09 21:27:32 CDT 2019",
        "user": "abdumali"
    },
    "963684": {
        "startTime": "Wed Oct 09 21:31:50 CDT 2019",
        "user": "abdumali"
    },
    "963687": {
        "startTime": "Wed Oct 09 21:32:58 CDT 2019",
        "user": "abdumali"
    },
    "963698": {
        "startTime": "Wed Oct 09 21:35:34 CDT 2019",
        "user": "abdumali"
    },
    "963701": {
        "startTime": "Wed Oct 09 21:35:34 CDT 2019",
        "user": "abdumali"
    },
    "963709": {
        "startTime": "Wed Oct 09 21:35:34 CDT 2019",
        "user": "abdumali"
    },
    "963717": {
        "startTime": "Wed Oct 09 21:35:34 CDT 2019",
        "user": "abdumali"
    },
    "963731": {
        "startTime": "Wed Oct 09 21:35:34 CDT 2019",
        "user": "abdumali"
    },
    "963742": {
        "startTime": "Wed Oct 09 21:35:34 CDT 2019",
        "user": "abdumali"
    },
    "963753": {
        "startTime": "Wed Oct 09 21:35:34 CDT 2019",
        "user": "abdumali"
    },
    "963758": {
        "startTime": "Wed Oct 09 21:35:34 CDT 2019",
        "user": "abdumali"
    },
    "963775": {
        "startTime": "Wed Oct 09 22:11:26 CDT 2019",
        "user": "abdumali"
    },
    "963789": {
        "startTime": "Wed Oct 09 22:12:55 CDT 2019",
        "user": "abdumali"
    },
    "963801": {
        "startTime": "Wed Oct 09 22:55:10 CDT 2019",
        "user": "abdumali"
    },
    "963802": {
        "startTime": "Wed Oct 09 22:55:10 CDT 2019",
        "user": "abdumali"
    },
    "963806": {
        "startTime": "Wed Oct 09 22:55:10 CDT 2019",
        "user": "abdumali"
    },
    "963823": {
        "startTime": "Wed Oct 09 23:10:33 CDT 2019",
        "user": "abdumali"
    },
    "963838": {
        "startTime": "Wed Oct 09 23:17:33 CDT 2019",
        "user": "abdumali"
    },
    "963848": {
        "startTime": "Wed Oct 09 23:23:10 CDT 2019",
        "user": "abdumali"
    },
    "963852": {
        "startTime": "Wed Oct 09 23:23:10 CDT 2019",
        "user": "abdumali"
    },
    "963904": {
        "startTime": "Wed Oct 09 22:58:44 CDT 2019",
        "user": "jjerke"
    },
    "963938": {
        "startTime": "Thu Oct 10 07:32:48 CDT 2019",
        "user": "samoradi"
    },
    "963940": {
        "startTime": "Thu Oct 10 07:54:59 CDT 2019",
        "user": "malooney"
    },
    "963948": {
        "startTime": "Thu Oct 10 09:17:35 CDT 2019",
        "user": "kmursi"
    },
    "963949": {
        "startTime": "Thu Oct 10 09:18:09 CDT 2019",
        "user": "kmursi"
    },
    "963957": {
        "startTime": "Thu Oct 10 09:24:35 CDT 2019",
        "user": "hge"
    },
    "963960": {
        "startTime": "Thu Oct 10 09:27:18 CDT 2019",
        "user": "gufeng"
    },
    "963961": {
        "startTime": "Thu Oct 10 09:27:36 CDT 2019",
        "user": "hge"
    },
    "963965": {
        "startTime": "Thu Oct 10 09:31:00 CDT 2019",
        "user": "johruska"
    },
    "963974": {
        "startTime": "Thu Oct 10 09:56:27 CDT 2019",
        "user": "aaljadda"
    },
    "963982": {
        "startTime": "Thu Oct 10 10:02:57 CDT 2019",
        "user": "dtarter"
    },
    "963983": {
        "startTime": "Thu Oct 10 10:03:07 CDT 2019",
        "user": "aaljadda"
    },
    "963995": {
        "startTime": "Thu Oct 10 10:26:58 CDT 2019",
        "user": "aaljadda"
    },
    "963998": {
        "startTime": "Thu Oct 10 10:29:13 CDT 2019",
        "user": "shahrahm"
    },
    "964014": {
        "startTime": "Thu Oct 10 10:36:42 CDT 2019",
        "user": "jjerke"
    },
    "964017": {
        "startTime": "Thu Oct 10 10:38:44 CDT 2019",
        "user": "jjerke"
    },
    "964021": {
        "startTime": "Thu Oct 10 10:46:24 CDT 2019",
        "user": "password"
    },
    "964031": {
        "startTime": "Thu Oct 10 11:26:05 CDT 2019",
        "user": "bithapal"
    },
    "964033": {
        "startTime": "Thu Oct 10 11:38:23 CDT 2019",
        "user": "npaulat"
    },
    "964041": {
        "startTime": "Thu Oct 10 11:42:16 CDT 2019",
        "user": "briasand"
    },
    "964044": {
        "startTime": "Thu Oct 10 12:14:26 CDT 2019",
        "user": "npaulat"
    },
    "964051": {
        "startTime": "Thu Oct 10 12:15:07 CDT 2019",
        "user": "npaulat"
    },
    "964059": {
        "startTime": "Thu Oct 10 11:53:50 CDT 2019",
        "user": "aaljadda"
    },
    "964062": {
        "startTime": "Thu Oct 10 12:07:16 CDT 2019",
        "user": "aaljadda"
    },
    "964069": {
        "startTime": "Thu Oct 10 12:15:57 CDT 2019",
        "user": "wang41"
    },
    "964074": {
        "startTime": "Thu Oct 10 12:47:33 CDT 2019",
        "user": "lediaz"
    },
    "964078": {
        "startTime": "Thu Oct 10 13:07:27 CDT 2019",
        "user": "gcapodag"
    },
    "964084": {
        "startTime": "Thu Oct 10 13:14:08 CDT 2019",
        "user": "bancell"
    },
    "964087": {
        "startTime": "Thu Oct 10 13:18:34 CDT 2019",
        "user": "sabaty"
    },
    "964090": {
        "startTime": "Thu Oct 10 14:28:38 CDT 2019",
        "user": "rmanser"
    },
    "964098": {
        "startTime": "Thu Oct 10 14:12:46 CDT 2019",
        "user": "aucolema"
    },
    "964099": {
        "startTime": "Thu Oct 10 14:13:20 CDT 2019",
        "user": "aucolema"
    },
    "964102": {
        "startTime": "Thu Oct 10 14:12:47 CDT 2019",
        "user": "password"
    },
    "964108": {
        "startTime": "Thu Oct 10 14:23:47 CDT 2019",
        "user": "sisadegh"
    },
    "964109": {
        "startTime": "Thu Oct 10 14:26:03 CDT 2019",
        "user": "sisadegh"
    },
    "964110": {
        "startTime": "Thu Oct 10 14:27:40 CDT 2019",
        "user": "sisadegh"
    },
    "964111": {
        "startTime": "Thu Oct 10 14:34:52 CDT 2019",
        "user": "sisadegh"
    },
    "964112": {
        "startTime": "Thu Oct 10 14:34:52 CDT 2019",
        "user": "sisadegh"
    },
    "964113": {
        "startTime": "Thu Oct 10 14:34:52 CDT 2019",
        "user": "sisadegh"
    },
    "964120": {
        "startTime": "Thu Oct 10 14:47:24 CDT 2019",
        "user": "janfisch"
    },
    "964121": {
        "startTime": "Thu Oct 10 14:45:27 CDT 2019",
        "user": "sabaty"
    },
    "964125": {
        "startTime": "Thu Oct 10 15:04:29 CDT 2019",
        "user": "gufeng"
    },
    "964127": {
        "startTime": "Thu Oct 10 14:57:35 CDT 2019",
        "user": "aaljadda"
    },
    "964129": {
        "startTime": "Thu Oct 10 14:53:52 CDT 2019",
        "user": "abkenyon"
    },
    "964131": {
        "startTime": "Thu Oct 10 15:08:12 CDT 2019",
        "user": "shahrahm"
    },
    "964133": {
        "startTime": "Thu Oct 10 15:00:23 CDT 2019",
        "user": "aaljadda"
    }
}